dubborequests/__init__.py
dubborequests/api.py
dubborequests/config.py
dubborequests/util.py
airdroptest-0.9.3.dist-info/LICENSE
airdroptest-0.9.3.dist-info/METADATA
airdroptest-0.9.3.dist-info/WHEEL
airdroptest-0.9.3.dist-info/top_level.txt
airdroptest-0.9.3.dist-info/RECORD
