Metadata-Version: 2.1
Name: airdroptest
Version: 0.9.3
Summary: Telnet command test dubbo
Home-page: https://github.com/airdrop11t/airdrop_test
Author: airdrop
Author-email: workspaceelojack@gmail.com
License: MIT
Classifier: Programming Language :: Python :: 3
Classifier: License :: OSI Approved :: MIT License
Classifier: Operating System :: OS Independent
Requires-Python: >=3.7.0
License-File: LICENSE
Requires-Dist: kazoo
